{"questions":[{"id":1,"question":"Hãy thực hiện yêu cầu trong hình","answer":"APEC","type":"TT_IMG","question_image":"Tangtoc1.png"},{"id":2,"question":"Hãy sắp xếp các thác nước sau theo thứ tự độ cao tăng dần","answer":"CABD","type":"TT_IMG","question_image":"Tangtoc2.png"},{"id":3,"question":"Tìm hình thích hợp điền vào khoảng trống","answer":"2 (Số chấm cột cuối bằng tích số chấm 3 cột đầu)","type":"TT_IMG","question_image":"Tangtoc3.jpg"},{"id":4,"question":"Đây là gì?","answer":"Đài Truyền hình Việt Nam/ VTV","type":"TT_VD","video_name":"Tangtoc4.mp4"}],"playerAnswers":[{"id":0,"answer":"","timestamp":0,"readableTime":"","correct":false},{"id":1,"answer":"","timestamp":0,"readableTime":"","correct":false},{"id":2,"answer":"","timestamp":0,"readableTime":"","correct":false},{"id":3,"answer":"","timestamp":0,"readableTime":"","correct":false}],"showResults":false,"currentQuestion":0,"showAnswer":false,"timerStartTimestamp":0}